.stestr.conf
.travis.yml
AUTHORS
ChangeLog
README.md
requirements.txt
setup.cfg
setup.py
test-requirements.txt
tox.ini
mlnx_switchdev_mode/__init__.py
mlnx_switchdev_mode/sriovify.py
mlnx_switchdev_mode.egg-info/PKG-INFO
mlnx_switchdev_mode.egg-info/SOURCES.txt
mlnx_switchdev_mode.egg-info/dependency_links.txt
mlnx_switchdev_mode.egg-info/entry_points.txt
mlnx_switchdev_mode.egg-info/not-zip-safe
mlnx_switchdev_mode.egg-info/pbr.json
mlnx_switchdev_mode.egg-info/requires.txt
mlnx_switchdev_mode.egg-info/top_level.txt
mlnx_switchdev_mode/tests/__init__.py
mlnx_switchdev_mode/tests/unit/__init__.py
mlnx_switchdev_mode/tests/unit/sys-bus-pci.txt
mlnx_switchdev_mode/tests/unit/test_sriovify.py
tools/mlnx-bind-vfs.service
tools/mlnx-switchdev-mode.service
tools/default/mlnx-switchdev-mode